{
  "type_description_msg": {
    "type_description": {
      "type_name": "automode_interfaces/action/Behavior_SendGoal_Event",
      "fields": [
        {
          "name": "info",
          "type": {
            "type_id": 1,
            "capacity": 0,
            "string_capacity": 0,
            "nested_type_name": "service_msgs/msg/ServiceEventInfo"
          },
          "default_value": ""
        },
        {
          "name": "request",
          "type": {
            "type_id": 97,
            "capacity": 1,
            "string_capacity": 0,
            "nested_type_name": "automode_interfaces/action/Behavior_SendGoal_Request"
          },
          "default_value": ""
        },
        {
          "name": "response",
          "type": {
            "type_id": 97,
            "capacity": 1,
            "string_capacity": 0,
            "nested_type_name": "automode_interfaces/action/Behavior_SendGoal_Response"
          },
          "default_value": ""
        }
      ]
    },
    "referenced_type_descriptions": [
      {
        "type_name": "automode_interfaces/action/Behavior_Goal",
        "fields": [
          {
            "name": "behavior_name",
            "type": {
              "type_id": 17,
              "capacity": 0,
              "string_capacity": 0,
              "nested_type_name": ""
            },
            "default_value": ""
          },
          {
            "name": "params",
            "type": {
              "type_id": 161,
              "capacity": 0,
              "string_capacity": 0,
              "nested_type_name": ""
            },
            "default_value": ""
          }
        ]
      },
      {
        "type_name": "automode_interfaces/action/Behavior_SendGoal_Request",
        "fields": [
          {
            "name": "goal_id",
            "type": {
              "type_id": 1,
              "capacity": 0,
              "string_capacity": 0,
              "nested_type_name": "unique_identifier_msgs/msg/UUID"
            },
            "default_value": ""
          },
          {
            "name": "goal",
            "type": {
              "type_id": 1,
              "capacity": 0,
              "string_capacity": 0,
              "nested_type_name": "automode_interfaces/action/Behavior_Goal"
            },
            "default_value": ""
          }
        ]
      },
      {
        "type_name": "automode_interfaces/action/Behavior_SendGoal_Response",
        "fields": [
          {
            "name": "accepted",
            "type": {
              "type_id": 15,
              "capacity": 0,
              "string_capacity": 0,
              "nested_type_name": ""
            },
            "default_value": ""
          },
          {
            "name": "stamp",
            "type": {
              "type_id": 1,
              "capacity": 0,
              "string_capacity": 0,
              "nested_type_name": "builtin_interfaces/msg/Time"
            },
            "default_value": ""
          }
        ]
      },
      {
        "type_name": "builtin_interfaces/msg/Time",
        "fields": [
          {
            "name": "sec",
            "type": {
              "type_id": 6,
              "capacity": 0,
              "string_capacity": 0,
              "nested_type_name": ""
            },
            "default_value": ""
          },
          {
            "name": "nanosec",
            "type": {
              "type_id": 7,
              "capacity": 0,
              "string_capacity": 0,
              "nested_type_name": ""
            },
            "default_value": ""
          }
        ]
      },
      {
        "type_name": "service_msgs/msg/ServiceEventInfo",
        "fields": [
          {
            "name": "event_type",
            "type": {
              "type_id": 3,
              "capacity": 0,
              "string_capacity": 0,
              "nested_type_name": ""
            },
            "default_value": ""
          },
          {
            "name": "stamp",
            "type": {
              "type_id": 1,
              "capacity": 0,
              "string_capacity": 0,
              "nested_type_name": "builtin_interfaces/msg/Time"
            },
            "default_value": ""
          },
          {
            "name": "client_gid",
            "type": {
              "type_id": 51,
              "capacity": 16,
              "string_capacity": 0,
              "nested_type_name": ""
            },
            "default_value": ""
          },
          {
            "name": "sequence_number",
            "type": {
              "type_id": 8,
              "capacity": 0,
              "string_capacity": 0,
              "nested_type_name": ""
            },
            "default_value": ""
          }
        ]
      },
      {
        "type_name": "unique_identifier_msgs/msg/UUID",
        "fields": [
          {
            "name": "uuid",
            "type": {
              "type_id": 51,
              "capacity": 16,
              "string_capacity": 0,
              "nested_type_name": ""
            },
            "default_value": ""
          }
        ]
      }
    ]
  },
  "type_hashes": [
    {
      "type_name": "automode_interfaces/action/Behavior_SendGoal_Event",
      "hash_string": "RIHS01_5bb7fe276e9d235b666a8afbdab2945b337380f18f61b9e78070a89e4a9ae9c0"
    },
    {
      "type_name": "automode_interfaces/action/Behavior_Goal",
      "hash_string": "RIHS01_78552dea4997055d180b9a86e646a88e7dd673b1604655f5589e1f27dacaf623"
    },
    {
      "type_name": "automode_interfaces/action/Behavior_SendGoal_Request",
      "hash_string": "RIHS01_2a0c01466470ee0d5cb7348ce0e7f72e01f419ddae683657e07c555af03a59e6"
    },
    {
      "type_name": "automode_interfaces/action/Behavior_SendGoal_Response",
      "hash_string": "RIHS01_f6c6cc79226029ed169d800fd980a74315690421fa7dd20d8232d6a483f6ab85"
    },
    {
      "type_name": "builtin_interfaces/msg/Time",
      "hash_string": "RIHS01_b106235e25a4c5ed35098aa0a61a3ee9c9b18d197f398b0e4206cea9acf9c197"
    },
    {
      "type_name": "service_msgs/msg/ServiceEventInfo",
      "hash_string": "RIHS01_41bcbbe07a75c9b52bc96bfd5c24d7f0fc0a08c0cb7921b3373c5732345a6f45"
    },
    {
      "type_name": "unique_identifier_msgs/msg/UUID",
      "hash_string": "RIHS01_1b8e8aca958cbea28fe6ef60bf6c19b683c97a9ef60bb34752067d0f2f7ab437"
    }
  ]
}